Workbook

Sheet Inputs
A1: FrankieOne — Singapore Unit Economics Model (Inputs)
A2: Variable | B2: Value | C2: Unit | D2: Notes / Source
A3: ACV | B3: 18000 | C3: USD/year | D3: Fixed single-tier contract value (case study assumption)
A4: MRR | B4: =B3/12 -> 1500 | C4: USD/month | D4: Derived: ACV / 12
A5: Gross margin | B5: 0.82 | C5: % | D5: From assumptions.yml
A6: CAC | B6: 14000 | C6: USD | D6: From assumptions.yml
A7: Monthly churn | B7: 0.018 | C7: % | D7: From assumptions.yml
A8: Sales cycle | B8: 2 | C8: months | D8: From assumptions.yml
A9: Market entry cost | B9: 500000 | C9: USD | D9: From assumptions.yml
A10: Monthly operating cost | B10: 25000 | C10: USD | D10: From assumptions.yml
A11: Leads per month | B11: 120 | C11: count | D11: From assumptions.yml
A12: Lead => Opportunity | B12: 0.18 | C12: % | D12: From assumptions.yml
A13: Opportunity => Win | B13: 0.22 | C13: % | D13: From assumptions.yml
A14: Wins per month | B14: =INT(INT(B11*B12)*B13) -> 4 | C14: count | D14: Baseline wins/month using repo INT logic (before market adjustment)
A15: Sales cycle (months) | B15: 2 | C15: months | D15: From repo funnel.sales_cycle_months
A16: Market adjustment (Singapore) | B16: 0.6081 | C16: multiplier | D16: Dashboard: (total_score+3)/6 clipped; SG total_score=0.6485478929
A17: Leads per month (adjusted) | B17: =INT(B11*B16) -> 72 | C17: count | D17: int(base_leads × market_adjustment)
A18: Wins per month (adjusted) | B18: =INT(INT(B17*B12)*B13) -> 2 | C18: count | D18: Repo INT truncation logic with adjusted leads

Sheet Unit Economics
A1: Unit Economics (Single Customer)
A2: Metric | B2: Value | C2: Unit | D2: Formula / Explanation
A3: MRR | B3: =Inputs!B4 -> 1500 | C3: USD/month | D3: Flat ACV / 12
A4: Gross profit per month | B4: =B3*Inputs!B5 -> 1230 | C4: USD/month | D4: MRR × Gross margin
A5: LTV (months) | B5: =1/Inputs!B7 -> 55.555556 | C5: months | D5: 1 / monthly churn
A6: LTV (gross profit) | B6: =B4*B5 -> 68333.333 | C6: USD | D6: Gross profit/month × LTV months
A7: CAC | B7: =Inputs!B6 -> 14000 | C7: USD | D7: Customer acquisition cost
A8: LTV:CAC | B8: =B6/B7 -> 4.8809524 | C8: x | D8: LTV (gross profit) / CAC
A9: CAC payback (months) | B9: =B7/B4 -> 11.382114 | C9: months | D9: CAC / gross profit per month

Sheet Customer Growth
A1: Customer Growth (12 Months)
A2: Month | B2: New customers | C2: Churned customers | D2: Active customers | E2: Notes
A3: 1 | B3: =IF(VALUE(A3)<Inputs!$B$15,0,Inputs!$B$18) -> 0 | C3: 0 | D3: =B3 -> 0 | E3: Churned customers display as 0 in the first 12 months because the model applies integer truncation: churned = INT(active × 1.8%). With active customers below ~56, INT(active × 0.018) remains 0.
A4: 2 | B4: =IF(VALUE(A4)<Inputs!$B$15,0,Inputs!$B$18) -> 2 | C4: =INT(D3*Inputs!$B$7) -> 0 | D4: =MAX(0,D3-C4+B4) -> 2
A5: 3 | B5: =IF(VALUE(A5)<Inputs!$B$15,0,Inputs!$B$18) -> 2 | C5: =INT(D4*Inputs!$B$7) -> 0 | D5: =MAX(0,D4-C5+B5) -> 4
A6: 4 | B6: =IF(VALUE(A6)<Inputs!$B$15,0,Inputs!$B$18) -> 2 | C6: =INT(D5*Inputs!$B$7) -> 0 | D6: =MAX(0,D5-C6+B6) -> 6
A7: 5 | B7: =IF(VALUE(A7)<Inputs!$B$15,0,Inputs!$B$18) -> 2 | C7: =INT(D6*Inputs!$B$7) -> 0 | D7: =MAX(0,D6-C7+B7) -> 8
A8: 6 | B8: =IF(VALUE(A8)<Inputs!$B$15,0,Inputs!$B$18) -> 2 | C8: =INT(D7*Inputs!$B$7) -> 0 | D8: =MAX(0,D7-C8+B8) -> 10
A9: 7 | B9: =IF(VALUE(A9)<Inputs!$B$15,0,Inputs!$B$18) -> 2 | C9: =INT(D8*Inputs!$B$7) -> 0 | D9: =MAX(0,D8-C9+B9) -> 12
A10: 8 | B10: =IF(VALUE(A10)<Inputs!$B$15,0,Inputs!$B$18) -> 2 | C10: =INT(D9*Inputs!$B$7) -> 0 | D10: =MAX(0,D9-C10+B10) -> 14
A11: 9 | B11: =IF(VALUE(A11)<Inputs!$B$15,0,Inputs!$B$18) -> 2 | C11: =INT(D10*Inputs!$B$7) -> 0 | D11: =MAX(0,D10-C11+B11) -> 16
A12: 10 | B12: =IF(VALUE(A12)<Inputs!$B$15,0,Inputs!$B$18) -> 2 | C12: =INT(D11*Inputs!$B$7) -> 0 | D12: =MAX(0,D11-C12+B12) -> 18
A13: 11 | B13: =IF(VALUE(A13)<Inputs!$B$15,0,Inputs!$B$18) -> 2 | C13: =INT(D12*Inputs!$B$7) -> 0 | D13: =MAX(0,D12-C13+B13) -> 20
A14: 12 | B14: =IF(VALUE(A14)<Inputs!$B$15,0,Inputs!$B$18) -> 2 | C14: =INT(D13*Inputs!$B$7) -> 0 | D14: =MAX(0,D13-C14+B14) -> 22
A16: Target (Month 12) | D16: =D14 -> 22

Sheet Revenue Model
A1: Revenue Model (12 Months)
A2: Month | B2: Active customers | C2: Revenue (monthly) | D2: Gross revenue (monthly) | E2: Acquisition cost (monthly) | F2: Net revenue (monthly) | G2: Cumulative net revenue
A3: 1 | B3: ='Customer Growth'!D3 -> 0 | C3: =B3*Inputs!$B$4 -> 0 | D3: =C3*Inputs!$B$5 -> 0 | E3: ='Customer Growth'!B3*Inputs!$B$6 -> 0 | F3: =D3-E3 -> 0 | G3: =F3 -> 0
A4: 2 | B4: ='Customer Growth'!D4 -> 2 | C4: =B4*Inputs!$B$4 -> 3000 | D4: =C4*Inputs!$B$5 -> 2460 | E4: ='Customer Growth'!B4*Inputs!$B$6 -> 28000 | F4: =D4-E4 -> -25540 | G4: =G3+F4 -> -25540
A5: 3 | B5: ='Customer Growth'!D5 -> 4 | C5: =B5*Inputs!$B$4 -> 6000 | D5: =C5*Inputs!$B$5 -> 4920 | E5: ='Customer Growth'!B5*Inputs!$B$6 -> 28000 | F5: =D5-E5 -> -23080 | G5: =G4+F5 -> -48620
A6: 4 | B6: ='Customer Growth'!D6 -> 6 | C6: =B6*Inputs!$B$4 -> 9000 | D6: =C6*Inputs!$B$5 -> 7380 | E6: ='Customer Growth'!B6*Inputs!$B$6 -> 28000 | F6: =D6-E6 -> -20620 | G6: =G5+F6 -> -69240
A7: 5 | B7: ='Customer Growth'!D7 -> 8 | C7: =B7*Inputs!$B$4 -> 12000 | D7: =C7*Inputs!$B$5 -> 9840 | E7: ='Customer Growth'!B7*Inputs!$B$6 -> 28000 | F7: =D7-E7 -> -18160 | G7: =G6+F7 -> -87400
A8: 6 | B8: ='Customer Growth'!D8 -> 10 | C8: =B8*Inputs!$B$4 -> 15000 | D8: =C8*Inputs!$B$5 -> 12300 | E8: ='Customer Growth'!B8*Inputs!$B$6 -> 28000 | F8: =D8-E8 -> -15700 | G8: =G7+F8 -> -103100
A9: 7 | B9: ='Customer Growth'!D9 -> 12 | C9: =B9*Inputs!$B$4 -> 18000 | D9: =C9*Inputs!$B$5 -> 14760 | E9: ='Customer Growth'!B9*Inputs!$B$6 -> 28000 | F9: =D9-E9 -> -13240 | G9: =G8+F9 -> -116340
A10: 8 | B10: ='Customer Growth'!D10 -> 14 | C10: =B10*Inputs!$B$4 -> 21000 | D10: =C10*Inputs!$B$5 -> 17220 | E10: ='Customer Growth'!B10*Inputs!$B$6 -> 28000 | F10: =D10-E10 -> -10780 | G10: =G9+F10 -> -127120
A11: 9 | B11: ='Customer Growth'!D11 -> 16 | C11: =B11*Inputs!$B$4 -> 24000 | D11: =C11*Inputs!$B$5 -> 19680 | E11: ='Customer Growth'!B11*Inputs!$B$6 -> 28000 | F11: =D11-E11 -> -8320 | G11: =G10+F11 -> -135440
A12: 10 | B12: ='Customer Growth'!D12 -> 18 | C12: =B12*Inputs!$B$4 -> 27000 | D12: =C12*Inputs!$B$5 -> 22140 | E12: ='Customer Growth'!B12*Inputs!$B$6 -> 28000 | F12: =D12-E12 -> -5860 | G12: =G11+F12 -> -141300
A13: 11 | B13: ='Customer Growth'!D13 -> 20 | C13: =B13*Inputs!$B$4 -> 30000 | D13: =C13*Inputs!$B$5 -> 24600 | E13: ='Customer Growth'!B13*Inputs!$B$6 -> 28000 | F13: =D13-E13 -> -3400 | G13: =G12+F13 -> -144700
A14: 12 | B14: ='Customer Growth'!D14 -> 22 | C14: =B14*Inputs!$B$4 -> 33000 | D14: =C14*Inputs!$B$5 -> 27060 | E14: ='Customer Growth'!B14*Inputs!$B$6 -> 28000 | F14: =D14-E14 -> -940 | G14: =G13+F14 -> -145640
A16: Totals (12m) | C16: =SUM(C3:C14) -> 198000 | D16: =SUM(D3:D14) -> 162360 | E16: =SUM(E3:E14) -> 308000 | F16: =SUM(F3:F14) -> -145640 | G16: =G14 -> -145640

Sheet Sensitivity
A1: Sensitivity (LTV:CAC)
B2: Churn 1.0% | C2: Churn 1.8% | D2: Churn 3.0% | F2: Notes
A3: CAC $10,000 | B3: =((Inputs!B4*Inputs!B5)*(1/0.01))/10000 -> 12.3 | C3: =((Inputs!B4*Inputs!B5)*(1/0.018))/10000 -> 6.8333333 | D3: =((Inputs!B4*Inputs!B5)*(1/0.03))/10000 -> 4.1 | F3: Higher is better
A4: CAC $14,000 | B4: =((Inputs!B4*Inputs!B5)*(1/0.01))/14000 -> 8.7857143 | C4: =((Inputs!B4*Inputs!B5)*(1/0.018))/14000 -> 4.8809524 | D4: =((Inputs!B4*Inputs!B5)*(1/0.03))/14000 -> 2.9285714 | F4: Higher is better
A5: CAC $18,000 | B5: =((Inputs!B4*Inputs!B5)*(1/0.01))/18000 -> 6.8333333 | C5: =((Inputs!B4*Inputs!B5)*(1/0.018))/18000 -> 3.7962963 | D5: =((Inputs!B4*Inputs!B5)*(1/0.03))/18000 -> 2.2777778 | F5: Higher is better
A7: Base case | B7: ='Unit Economics'!B8 -> 4.8809524
